AUTHORS
LICENSE
MANIFEST.in
README.md
setup.py
django_rest_common.egg-info/PKG-INFO
django_rest_common.egg-info/SOURCES.txt
django_rest_common.egg-info/dependency_links.txt
django_rest_common.egg-info/not-zip-safe
django_rest_common.egg-info/requires.txt
django_rest_common.egg-info/top_level.txt
rest_common/__init__.py
rest_common/authentication.py
rest_common/fields.py
rest_common/middleware.py
rest_common/serializers.py
rest_common/tests.py
rest_common/views.py