Metadata-Version: 1.1
Name: django-rest-common
Version: 0.0.6
Summary: Common things every Django REST app needs!
Home-page: http://github.com/Tivix/django-rest-common
Author: Sumit Chachra
Author-email: chachra@tivix.com
License: UNKNOWN
Keywords: django rest common rest-framework api
Platform: UNKNOWN
Classifier: Framework :: Django
Classifier: Intended Audience :: Developers
Classifier: Intended Audience :: System Administrators
Classifier: Operating System :: OS Independent
Classifier: Topic :: Software Development
